Workbook

Sheet Controls
A1: Workbook Controls
A3: Report Date | B3: 46119
A5: Project Statuses | B5: Invoice Statuses | C5: Document Statuses | D5: Pipeline Stages | E5: Inventory Flags
A6: Planning | B6: Draft | C6: Open | D6: Setup | E6: OK
A7: Active | B7: Submitted | C7: Pending | D7: Procurement | E7: Reorder
A8: Billing | B8: Approved | C8: Approved | D8: Field Install | E8: On Order
A9: Closeout | B9: Partial | C9: Closed | D9: Testing | E9: Issued
A10: Closed | B10: Paid | D10: Billing
A11: On Hold | B11: Overdue | D11: Closeout

Sheet Project Dashboard
A1: LINX Project Operations Dashboard
A2: Report Date | B2: =Controls!$B$3 -> 46119 | D2: Sample dashboard for interviews — built in Excel to simulate project setup, billing, document control, inventory, and closeout tracking.
A3: Open Projects | D3: Total Revised Budget | G3: Total Actual Cost | J3: Gross Remaining | M3: Outstanding A/R | R3: Status | S3: Count
A4: =COUNTIF(G11:G16,"<>Closed") -> 5 | D4: =SUM(K11:K16) -> 644000 | G4: =SUM(L11:L16) -> 467300 | J4: =SUM(M11:M16) -> 176700 | M4: =SUM(P11:P16) -> 81000 | R4: Planning | S4: =COUNTIF(G11:G16,R4) -> 1
A5: Overdue Docs | D5: Reorder Alerts | G5: Open Invoices | J5: Avg Completion | M5: Projects Over Budget | R5: Active | S5: =COUNTIF(G11:G16,R5) -> 2
A6: =COUNTIF('Document Control'!J5:J16,"Yes") -> 3 | D6: =COUNTIF('Inventory Tracker'!I5:I13,"Reorder") -> 4 | G6: =COUNTIF('Billing Tracker'!J5:J14,"<>Paid") -> 6 | J6: =AVERAGE(H11:H16) -> 0.76166667 | M6: =COUNTIF(M11:M16,"<0") -> 0 | R6: Billing | S6: =COUNTIF(G11:G16,R6) -> 1
R7: Closeout | S7: =COUNTIF(G11:G16,R7) -> 1
R8: Closed | S8: =COUNTIF(G11:G16,R8) -> 1
A10: Project ID | B10: Project Name | C10: Office | D10: Project Manager | E10: Start Date | F10: End Date | G10: Status | H10: % Complete | I10: Base Budget | J10: Approved COs | K10: Revised Budget | L10: Actual Cost | M10: Cost Variance | N10: Billed To Date | O10: Cash Received | P10: Outstanding AR | R10: Project | S10: Revised Budget | T10: Actual Cost | U10: Outstanding AR
A11: P-1001 | B11: Denver Data Center Buildout | C11: Denver | D11: Riley Chen | E11: 46034 | F11: 46171 | G11: Active | H11: 0.65 | I11: 185000 | J11: 18000 | K11: =I11+J11 -> 203000 | L11: 126500 | M11: =K11-L11 -> 76500 | N11: 118000 | O11: 90000 | P11: =N11-O11 -> 28000 | R11: =B11 -> Denver Data Center Buildout | S11: =K11 -> 203000 | T11: =L11 -> 126500 | U11: =P11 -> 28000
A12: P-1002 | B12: Seattle Office Security Upgrade | C12: Seattle | D12: Morgan Lee | E12: 46055 | F12: 46136 | G12: Billing | H12: 0.92 | I12: 72000 | J12: 4500 | K12: =I12+J12 -> 76500 | L12: 68100 | M12: =K12-L12 -> 8400 | N12: 74500 | O12: 61000 | P12: =N12-O12 -> 13500 | R12: =B12 -> Seattle Office Security Upgrade | S12: =K12 -> 76500 | T12: =L12 -> 68100 | U12: =P12 -> 13500
A13: P-1003 | B13: Salt Lake Wireless Refresh | C13: Salt Lake City | D13: Jordan Patel | E13: 46071 | F13: 46185 | G13: Planning | H13: 0.24 | I13: 94000 | J13: 0 | K13: =I13+J13 -> 94000 | L13: 18250 | M13: =K13-L13 -> 75750 | N13: 15000 | O13: 0 | P13: =N13-O13 -> 15000 | R13: =B13 -> Salt Lake Wireless Refresh | S13: =K13 -> 94000 | T13: =L13 -> 18250 | U13: =P13 -> 15000
A14: P-1004 | B14: San Antonio Cabling Retrofit | C14: San Antonio | D14: Avery Brooks | E14: 45999 | F14: 46101 | G14: Closeout | H14: 0.98 | I14: 128000 | J14: 12000 | K14: =I14+J14 -> 140000 | L14: 137900 | M14: =K14-L14 -> 2100 | N14: 141000 | O14: 134500 | P14: =N14-O14 -> 6500 | R14: =B14 -> San Antonio Cabling Retrofit | S14: =K14 -> 140000 | T14: =L14 -> 137900 | U14: =P14 -> 6500
A15: P-1005 | B15: Atlanta Access Control Install | C15: Atlanta | D15: Taylor Nguyen | E15: 46049 | F15: 46142 | G15: Active | H15: 0.78 | I15: 86000 | J15: 6500 | K15: =I15+J15 -> 92500 | L15: 80100 | M15: =K15-L15 -> 12400 | N15: 70000 | O15: 52000 | P15: =N15-O15 -> 18000 | R15: =B15 -> Atlanta Access Control Install | S15: =K15 -> 92500 | T15: =L15 -> 80100 | U15: =P15 -> 18000
A16: P-1006 | B16: Cheyenne MDF/IDF Cleanup | C16: Cheyenne | D16: Casey Smith | E16: 46028 | F16: 46081 | G16: Closed | H16: 1 | I16: 38000 | J16: 0 | K16: =I16+J16 -> 38000 | L16: 36450 | M16: =K16-L16 -> 1550 | N16: 38200 | O16: 38200 | P16: =N16-O16 -> 0 | R16: =B16 -> Cheyenne MDF/IDF Cleanup | S16: =K16 -> 38000 | T16: =L16 -> 36450 | U16: =P16 -> 0

Sheet Billing Tracker
A1: Billing Tracker & A/R Aging
A2: Total Gross Billings | D2: Net Billable | G2: Cash Received | J2: Current A/R
A3: =SUM(E5:E14) -> 338700 | D3: =SUM(G5:G14) -> 311875 | G3: =SUM(H5:H14) -> 175500 | J3: =SUM(G5:G14)-SUM(H5:H14) -> 136375
A4: Invoice # | B4: Project ID | C4: Project Name | D4: Invoice Date | E4: Invoice Amount | F4: Retainage % | G4: Net Billable | H4: Paid Amount | I4: Payment Date | J4: Payment Status | K4: Days Outstanding | L4: Aging Bucket | N4: Aging Bucket | O4: Open $
A5: INV-26001 | B5: P-1001 | C5: Denver Data Center Buildout | D5: 46081 | E5: 42000 | F5: 0.1 | G5: =E5*(1-F5) -> 37800 | H5: 25000 | I5: 46101 | J5: Partial | K5: =IF(J5="Paid",I5-D5,Controls!$B$3-D5) -> 38 | L5: =IF(K5<=30,"0-30",IF(K5<=60,"31-60",IF(K5<=90,"61-90","90+"))) -> 31-60 | N5: 0-30 | O5: =SUMIFS(G$5:G$14,L$5:L$14,N5,J$5:J$14,"<>Paid") -> 142075
A6: INV-26002 | B6: P-1001 | C6: Denver Data Center Buildout | D6: 46112 | E6: 38000 | F6: 0.1 | G6: =E6*(1-F6) -> 34200 | H6: 0 | J6: Submitted | K6: =IF(J6="Paid",I6-D6,Controls!$B$3-D6) -> 7 | L6: =IF(K6<=30,"0-30",IF(K6<=60,"31-60",IF(K6<=90,"61-90","90+"))) -> 0-30 | N6: 31-60 | O6: =SUMIFS(G$5:G$14,L$5:L$14,N6,J$5:J$14,"<>Paid") -> 37800
A7: INV-26003 | B7: P-1002 | C7: Seattle Office Security Upgrade | D7: 46096 | E7: 26000 | F7: 0.05 | G7: =E7*(1-F7) -> 24700 | H7: 26000 | I7: 46114 | J7: Paid | K7: =IF(J7="Paid",I7-D7,Controls!$B$3-D7) -> 18 | L7: =IF(K7<=30,"0-30",IF(K7<=60,"31-60",IF(K7<=90,"61-90","90+"))) -> 0-30 | N7: 61-90 | O7: =SUMIFS(G$5:G$14,L$5:L$14,N7,J$5:J$14,"<>Paid") -> 0
A8: INV-26004 | B8: P-1003 | C8: Salt Lake Wireless Refresh | D8: 46110 | E8: 15000 | F8: 0 | G8: =E8*(1-F8) -> 15000 | H8: 0 | J8: Approved | K8: =IF(J8="Paid",I8-D8,Controls!$B$3-D8) -> 9 | L8: =IF(K8<=30,"0-30",IF(K8<=60,"31-60",IF(K8<=90,"61-90","90+"))) -> 0-30 | N8: 90+ | O8: =SUMIFS(G$5:G$14,L$5:L$14,N8,J$5:J$14,"<>Paid") -> 0
A9: INV-26005 | B9: P-1004 | C9: San Antonio Cabling Retrofit | D9: 46071 | E9: 47000 | F9: 0.1 | G9: =E9*(1-F9) -> 42300 | H9: 42300 | I9: 46109 | J9: Paid | K9: =IF(J9="Paid",I9-D9,Controls!$B$3-D9) -> 38 | L9: =IF(K9<=30,"0-30",IF(K9<=60,"31-60",IF(K9<=90,"61-90","90+"))) -> 31-60
A10: INV-26006 | B10: P-1005 | C10: Atlanta Access Control Install | D10: 46089 | E10: 30000 | F10: 0.1 | G10: =E10*(1-F10) -> 27000 | H10: 12000 | I10: 46113 | J10: Partial | K10: =IF(J10="Paid",I10-D10,Controls!$B$3-D10) -> 30 | L10: =IF(K10<=30,"0-30",IF(K10<=60,"31-60",IF(K10<=90,"61-90","90+"))) -> 0-30
A11: INV-26007 | B11: P-1005 | C11: Atlanta Access Control Install | D11: 46116 | E11: 22000 | F11: 0.1 | G11: =E11*(1-F11) -> 19800 | H11: 0 | J11: Draft | K11: =IF(J11="Paid",I11-D11,Controls!$B$3-D11) -> 3 | L11: =IF(K11<=30,"0-30",IF(K11<=60,"31-60",IF(K11<=90,"61-90","90+"))) -> 0-30
A12: INV-26008 | B12: P-1006 | C12: Cheyenne MDF/IDF Cleanup | D12: 46064 | E12: 18200 | F12: 0 | G12: =E12*(1-F12) -> 18200 | H12: 18200 | I12: 46078 | J12: Paid | K12: =IF(J12="Paid",I12-D12,Controls!$B$3-D12) -> 14 | L12: =IF(K12<=30,"0-30",IF(K12<=60,"31-60",IF(K12<=90,"61-90","90+"))) -> 0-30
A13: INV-26009 | B13: P-1002 | C13: Seattle Office Security Upgrade | D13: 46113 | E13: 48500 | F13: 0.05 | G13: =E13*(1-F13) -> 46075 | H13: 0 | J13: Submitted | K13: =IF(J13="Paid",I13-D13,Controls!$B$3-D13) -> 6 | L13: =IF(K13<=30,"0-30",IF(K13<=60,"31-60",IF(K13<=90,"61-90","90+"))) -> 0-30
A14: INV-26010 | B14: P-1004 | C14: San Antonio Cabling Retrofit | D14: 46052 | E14: 52000 | F14: 0.1 | G14: =E14*(1-F14) -> 46800 | H14: 52000 | I14: 46086 | J14: Paid | K14: =IF(J14="Paid",I14-D14,Controls!$B$3-D14) -> 34 | L14: =IF(K14<=30,"0-30",IF(K14<=60,"31-60",IF(K14<=90,"61-90","90+"))) -> 31-60

Sheet Document Control
A1: Document Control Log
A2: Track RFIs, submittals, and closeout documents with due dates and overdue flags. | M2: Open Items | P2: Overdue Items | S2: Closed / Approved
M3: =COUNTIF(H5:H16,"Open")+COUNTIF(H5:H16,"Pending") -> 7 | P3: =COUNTIF(J5:J16,"Yes") -> 3 | S3: =COUNTIF(H5:H16,"Closed")+COUNTIF(H5:H16,"Approved") -> 5
A4: Doc ID | B4: Project ID | C4: Project Name | D4: Document Type | E4: Description | F4: Date Submitted | G4: Due Date | H4: Status | I4: Owner | J4: Overdue? | K4: Days Open
A5: RFI-101 | B5: P-1001 | C5: Denver Data Center Buildout | D5: RFI | E5: Conduit routing clarification | F5: 46093 | G5: 46100 | H5: Closed | I5: Riley Chen | J5: =IF(OR(H5="Closed",H5="Approved"),"No",IF(G5<Controls!$B$3,"Yes","No")) -> No | K5: =IF(OR(H5="Closed",H5="Approved"),G5-F5,Controls!$B$3-F5) -> 7 | M5: Status | N5: Count
A6: SUB-204 | B6: P-1001 | C6: Denver Data Center Buildout | D6: Submittal | E6: Cable schedule package | F6: 46109 | G6: 46120 | H6: Pending | I6: Morgan Lee | J6: =IF(OR(H6="Closed",H6="Approved"),"No",IF(G6<Controls!$B$3,"Yes","No")) -> No | K6: =IF(OR(H6="Closed",H6="Approved"),G6-F6,Controls!$B$3-F6) -> 10 | M6: Open | N6: =COUNTIF(H5:H16,M6) -> 3
A7: RFI-118 | B7: P-1002 | C7: Seattle Office Security Upgrade | D7: RFI | E7: Door hardware coordination | F7: 46107 | G7: 46113 | H7: Approved | I7: Jordan Patel | J7: =IF(OR(H7="Closed",H7="Approved"),"No",IF(G7<Controls!$B$3,"Yes","No")) -> No | K7: =IF(OR(H7="Closed",H7="Approved"),G7-F7,Controls!$B$3-F7) -> 6 | M7: Pending | N7: =COUNTIF(H5:H16,M7) -> 4
A8: SUB-208 | B8: P-1003 | C8: Salt Lake Wireless Refresh | D8: Submittal | E8: AP mounting details | F8: 46113 | G8: 46124 | H8: Open | I8: Taylor Nguyen | J8: =IF(OR(H8="Closed",H8="Approved"),"No",IF(G8<Controls!$B$3,"Yes","No")) -> No | K8: =IF(OR(H8="Closed",H8="Approved"),G8-F8,Controls!$B$3-F8) -> 6 | M8: Approved | N8: =COUNTIF(H5:H16,M8) -> 2
A9: RFI-127 | B9: P-1004 | C9: San Antonio Cabling Retrofit | D9: RFI | E9: Above-ceiling access request | F9: 46086 | G9: 46093 | H9: Closed | I9: Avery Brooks | J9: =IF(OR(H9="Closed",H9="Approved"),"No",IF(G9<Controls!$B$3,"Yes","No")) -> No | K9: =IF(OR(H9="Closed",H9="Approved"),G9-F9,Controls!$B$3-F9) -> 7 | M9: Closed | N9: =COUNTIF(H5:H16,M9) -> 3
A10: CLS-001 | B10: P-1004 | C10: San Antonio Cabling Retrofit | D10: Closeout | E10: Warranty letter draft | F10: 46102 | G10: 46112 | H10: Pending | I10: Casey Smith | J10: =IF(OR(H10="Closed",H10="Approved"),"No",IF(G10<Controls!$B$3,"Yes","No")) -> Yes | K10: =IF(OR(H10="Closed",H10="Approved"),G10-F10,Controls!$B$3-F10) -> 17
A11: RFI-133 | B11: P-1005 | C11: Atlanta Access Control Install | D11: RFI | E11: Panel location confirmation | F11: 46110 | G11: 46115 | H11: Open | I11: Taylor Nguyen | J11: =IF(OR(H11="Closed",H11="Approved"),"No",IF(G11<Controls!$B$3,"Yes","No")) -> Yes | K11: =IF(OR(H11="Closed",H11="Approved"),G11-F11,Controls!$B$3-F11) -> 9
A12: SUB-211 | B12: P-1005 | C12: Atlanta Access Control Install | D12: Submittal | E12: Device cut sheet package | F12: 46111 | G12: 46118 | H12: Pending | I12: Morgan Lee | J12: =IF(OR(H12="Closed",H12="Approved"),"No",IF(G12<Controls!$B$3,"Yes","No")) -> Yes | K12: =IF(OR(H12="Closed",H12="Approved"),G12-F12,Controls!$B$3-F12) -> 8
A13: CLS-002 | B13: P-1006 | C13: Cheyenne MDF/IDF Cleanup | D13: Closeout | E13: As-built markup | F13: 46071 | G13: 46081 | H13: Approved | I13: Riley Chen | J13: =IF(OR(H13="Closed",H13="Approved"),"No",IF(G13<Controls!$B$3,"Yes","No")) -> No | K13: =IF(OR(H13="Closed",H13="Approved"),G13-F13,Controls!$B$3-F13) -> 10
A14: SUB-198 | B14: P-1002 | C14: Seattle Office Security Upgrade | D14: Submittal | E14: Panel schedules | F14: 46091 | G14: 46098 | H14: Closed | I14: Jordan Patel | J14: =IF(OR(H14="Closed",H14="Approved"),"No",IF(G14<Controls!$B$3,"Yes","No")) -> No | K14: =IF(OR(H14="Closed",H14="Approved"),G14-F14,Controls!$B$3-F14) -> 7
A15: RFI-139 | B15: P-1001 | C15: Denver Data Center Buildout | D15: RFI | E15: Rack elevation confirmation | F15: 46114 | G15: 46121 | H15: Open | I15: Riley Chen | J15: =IF(OR(H15="Closed",H15="Approved"),"No",IF(G15<Controls!$B$3,"Yes","No")) -> No | K15: =IF(OR(H15="Closed",H15="Approved"),G15-F15,Controls!$B$3-F15) -> 5
A16: CLS-003 | B16: P-1005 | C16: Atlanta Access Control Install | D16: Closeout | E16: O&M draft | F16: 46115 | G16: 46127 | H16: Pending | I16: Avery Brooks | J16: =IF(OR(H16="Closed",H16="Approved"),"No",IF(G16<Controls!$B$3,"Yes","No")) -> No | K16: =IF(OR(H16="Closed",H16="Approved"),G16-F16,Controls!$B$3-F16) -> 4

Sheet Inventory Tracker
A1: Inventory & Procurement Tracker
A2: Consumables and job-site materials with reorder automation. | L2: Stock Value | O2: Items to Reorder | R2: Items On Order
L3: =SUM(J5:J13) -> 8717 | O3: =COUNTIF(I5:I13,"Reorder") -> 4 | R3: =COUNTIF(I5:I13,"On Order") -> 1
A4: Item ID | B4: Item Name | C4: Category | D4: Location | E4: Unit Cost | F4: Qty On Hand | G4: Reorder Point | H4: Qty On Order | I4: Reorder Flag | J4: Stock Value
A5: MAT-001 | B5: Cat6A Cable Box | C5: Cabling | D5: Denver Yard | E5: 185 | F5: 12 | G5: 8 | H5: 6 | I5: =IF(F5<=G5,"Reorder",IF(H5>0,"On Order","OK")) -> On Order | J5: =E5*F5 -> 2220 | L5: Category | M5: Stock Value
A6: MAT-002 | B6: Patch Panels | C6: Hardware | D6: Seattle Office | E6: 140 | F6: 4 | G6: 6 | H6: 8 | I6: =IF(F6<=G6,"Reorder",IF(H6>0,"On Order","OK")) -> Reorder | J6: =E6*F6 -> 560 | L6: Cabling | M6: =SUMIFS(J$5:J$13,C$5:C$13,L6) -> 2220
A7: MAT-003 | B7: Faceplates | C7: Consumable | D7: Atlanta Office | E7: 3 | F7: 175 | G7: 120 | H7: 0 | I7: =IF(F7<=G7,"Reorder",IF(H7>0,"On Order","OK")) -> OK | J7: =E7*F7 -> 525 | L7: Hardware | M7: =SUMIFS(J$5:J$13,C$5:C$13,L7) -> 1210
A8: MAT-004 | B8: Velcro Ties | C8: Consumable | D8: San Antonio Office | E8: 12 | F8: 15 | G8: 20 | H8: 25 | I8: =IF(F8<=G8,"Reorder",IF(H8>0,"On Order","OK")) -> Reorder | J8: =E8*F8 -> 180 | L8: Consumable | M8: =SUMIFS(J$5:J$13,C$5:C$13,L8) -> 777
A9: MAT-005 | B9: Security Readers | C9: Security | D9: Atlanta Office | E9: 420 | F9: 9 | G9: 6 | H9: 0 | I9: =IF(F9<=G9,"Reorder",IF(H9>0,"On Order","OK")) -> OK | J9: =E9*F9 -> 3780 | L9: Security | M9: =SUMIFS(J$5:J$13,C$5:C$13,L9) -> 3780
A10: MAT-006 | B10: Fiber Shelf | C10: Hardware | D10: Denver Yard | E10: 325 | F10: 2 | G10: 3 | H10: 2 | I10: =IF(F10<=G10,"Reorder",IF(H10>0,"On Order","OK")) -> Reorder | J10: =E10*F10 -> 650 | L10: Field Support | M10: =SUMIFS(J$5:J$13,C$5:C$13,L10) -> 240
A11: MAT-007 | B11: Ice / Water Coolers | C11: Field Support | D11: Salt Lake City | E11: 48 | F11: 5 | G11: 4 | H11: 0 | I11: =IF(F11<=G11,"Reorder",IF(H11>0,"On Order","OK")) -> OK | J11: =E11*F11 -> 240 | L11: Safety | M11: =SUMIFS(J$5:J$13,C$5:C$13,L11) -> 490
A12: MAT-008 | B12: PPE Kits | C12: Safety | D12: Seattle Office | E12: 35 | F12: 14 | G12: 10 | H12: 0 | I12: =IF(F12<=G12,"Reorder",IF(H12>0,"On Order","OK")) -> OK | J12: =E12*F12 -> 490
A13: MAT-009 | B13: Labels & Heat Shrink | C13: Consumable | D13: Cheyenne Office | E13: 24 | F13: 3 | G13: 5 | H13: 10 | I13: =IF(F13<=G13,"Reorder",IF(H13>0,"On Order","OK")) -> Reorder | J13: =E13*F13 -> 72

Sheet Workflow Pipeline
A1: Workflow Pipeline & Stage Timeline
A2: The weekly timeline highlights the current-stage window for each project.
A4: Project ID | B4: Project Name | C4: Current Stage | D4: Stage Owner | E4: Stage Start | F4: Planned Finish | G4: Actual Finish | H4: Days in Stage | I4: Stage Status | J4: Next Milestone | K4: 46090 | L4: 46097 | M4: 46104 | N4: 46111 | O4: 46118 | P4: 46125 | Q4: 46132 | R4: 46139
A5: P-1001 | B5: Denver Data Center Buildout | C5: Field Install | D5: Riley Chen | E5: 46104 | F5: 46129 | H5: =IF(G5<>"",G5-E5,Controls!$B$3-E5) -> 15 | I5: On Track | J5: Begin testing 4/20 | K5: =IF(AND(K$4>=$E5,K$4<=$F5),1,"") | L5: =IF(AND(L$4>=$E5,L$4<=$F5),1,"") | M5: =IF(AND(M$4>=$E5,M$4<=$F5),1,"") -> 1 | N5: =IF(AND(N$4>=$E5,N$4<=$F5),1,"") -> 1 | O5: =IF(AND(O$4>=$E5,O$4<=$F5),1,"") -> 1 | P5: =IF(AND(P$4>=$E5,P$4<=$F5),1,"") -> 1 | Q5: =IF(AND(Q$4>=$E5,Q$4<=$F5),1,"") | R5: =IF(AND(R$4>=$E5,R$4<=$F5),1,"")
A6: P-1002 | B6: Seattle Office Security Upgrade | C6: Billing | D6: Morgan Lee | E6: 46105 | F6: 46122 | H6: =IF(G6<>"",G6-E6,Controls!$B$3-E6) -> 14 | I6: At Risk | J6: Submit final pay app | K6: =IF(AND(K$4>=$E6,K$4<=$F6),1,"") | L6: =IF(AND(L$4>=$E6,L$4<=$F6),1,"") | M6: =IF(AND(M$4>=$E6,M$4<=$F6),1,"") | N6: =IF(AND(N$4>=$E6,N$4<=$F6),1,"") -> 1 | O6: =IF(AND(O$4>=$E6,O$4<=$F6),1,"") -> 1 | P6: =IF(AND(P$4>=$E6,P$4<=$F6),1,"") | Q6: =IF(AND(Q$4>=$E6,Q$4<=$F6),1,"") | R6: =IF(AND(R$4>=$E6,R$4<=$F6),1,"")
A7: P-1003 | B7: Salt Lake Wireless Refresh | C7: Procurement | D7: Jordan Patel | E7: 46111 | F7: 46136 | H7: =IF(G7<>"",G7-E7,Controls!$B$3-E7) -> 8 | I7: On Track | J7: Release AP order | K7: =IF(AND(K$4>=$E7,K$4<=$F7),1,"") | L7: =IF(AND(L$4>=$E7,L$4<=$F7),1,"") | M7: =IF(AND(M$4>=$E7,M$4<=$F7),1,"") | N7: =IF(AND(N$4>=$E7,N$4<=$F7),1,"") -> 1 | O7: =IF(AND(O$4>=$E7,O$4<=$F7),1,"") -> 1 | P7: =IF(AND(P$4>=$E7,P$4<=$F7),1,"") -> 1 | Q7: =IF(AND(Q$4>=$E7,Q$4<=$F7),1,"") -> 1 | R7: =IF(AND(R$4>=$E7,R$4<=$F7),1,"")
A8: P-1004 | B8: San Antonio Cabling Retrofit | C8: Closeout | D8: Avery Brooks | E8: 46097 | F8: 46121 | H8: =IF(G8<>"",G8-E8,Controls!$B$3-E8) -> 22 | I8: Needs Review | J8: Finalize warranty letter | K8: =IF(AND(K$4>=$E8,K$4<=$F8),1,"") | L8: =IF(AND(L$4>=$E8,L$4<=$F8),1,"") -> 1 | M8: =IF(AND(M$4>=$E8,M$4<=$F8),1,"") -> 1 | N8: =IF(AND(N$4>=$E8,N$4<=$F8),1,"") -> 1 | O8: =IF(AND(O$4>=$E8,O$4<=$F8),1,"") -> 1 | P8: =IF(AND(P$4>=$E8,P$4<=$F8),1,"") | Q8: =IF(AND(Q$4>=$E8,Q$4<=$F8),1,"") | R8: =IF(AND(R$4>=$E8,R$4<=$F8),1,"")
A9: P-1005 | B9: Atlanta Access Control Install | C9: Field Install | D9: Taylor Nguyen | E9: 46098 | F9: 46134 | H9: =IF(G9<>"",G9-E9,Controls!$B$3-E9) -> 21 | I9: On Track | J9: Program readers 4/14 | K9: =IF(AND(K$4>=$E9,K$4<=$F9),1,"") | L9: =IF(AND(L$4>=$E9,L$4<=$F9),1,"") | M9: =IF(AND(M$4>=$E9,M$4<=$F9),1,"") -> 1 | N9: =IF(AND(N$4>=$E9,N$4<=$F9),1,"") -> 1 | O9: =IF(AND(O$4>=$E9,O$4<=$F9),1,"") -> 1 | P9: =IF(AND(P$4>=$E9,P$4<=$F9),1,"") -> 1 | Q9: =IF(AND(Q$4>=$E9,Q$4<=$F9),1,"") -> 1 | R9: =IF(AND(R$4>=$E9,R$4<=$F9),1,"")
A10: P-1006 | B10: Cheyenne MDF/IDF Cleanup | C10: Closed | D10: Casey Smith | E10: 46063 | F10: 46081 | G10: 46080 | H10: =IF(G10<>"",G10-E10,Controls!$B$3-E10) -> 17 | I10: Complete | J10: Archive project files | K10: =IF(AND(K$4>=$E10,K$4<=$F10),1,"") | L10: =IF(AND(L$4>=$E10,L$4<=$F10),1,"") | M10: =IF(AND(M$4>=$E10,M$4<=$F10),1,"") | N10: =IF(AND(N$4>=$E10,N$4<=$F10),1,"") | O10: =IF(AND(O$4>=$E10,O$4<=$F10),1,"") | P10: =IF(AND(P$4>=$E10,P$4<=$F10),1,"") | Q10: =IF(AND(Q$4>=$E10,Q$4<=$F10),1,"") | R10: =IF(AND(R$4>=$E10,R$4<=$F10),1,"")
